movici_simulation_core/__init__.py
movici_simulation_core/attributes.py
movici_simulation_core/csr.py
movici_simulation_core/exceptions.py
movici_simulation_core/messages.py
movici_simulation_core/settings.py
movici_simulation_core/simulation.py
movici_simulation_core/types.py
movici_simulation_core/validate.py
movici_simulation_core/ae_wrapper/__init__.py
movici_simulation_core/ae_wrapper/collections.py
movici_simulation_core/ae_wrapper/id_generator.py
movici_simulation_core/ae_wrapper/patches.py
movici_simulation_core/ae_wrapper/point_generator.py
movici_simulation_core/ae_wrapper/project.py
movici_simulation_core/base_models/__init__.py
movici_simulation_core/base_models/common.py
movici_simulation_core/base_models/simple_model.py
movici_simulation_core/base_models/tracked_model.py
movici_simulation_core/core/__init__.py
movici_simulation_core/core/arrays.py
movici_simulation_core/core/attribute.py
movici_simulation_core/core/attribute_spec.py
movici_simulation_core/core/data_format.py
movici_simulation_core/core/data_type.py
movici_simulation_core/core/entity_group.py
movici_simulation_core/core/index.py
movici_simulation_core/core/moment.py
movici_simulation_core/core/numba_extensions.py
movici_simulation_core/core/schema.py
movici_simulation_core/core/serialization.py
movici_simulation_core/core/state.py
movici_simulation_core/core/types.py
movici_simulation_core/core/utils.py
movici_simulation_core/json_schemas/__init__.py
movici_simulation_core/json_schemas/dataset_creator.json
movici_simulation_core/json_schemas/models/__init__.py
movici_simulation_core/json_schemas/models/area_aggregation.json
movici_simulation_core/json_schemas/models/corridor.json
movici_simulation_core/json_schemas/models/csv_player.json
movici_simulation_core/json_schemas/models/data_collector.json
movici_simulation_core/json_schemas/models/evacuation_point_resolution.json
movici_simulation_core/json_schemas/models/generalized_journey_time.json
movici_simulation_core-2.10.6.dist-info/LICENSE
movici_simulation_core-2.10.6.dist-info/METADATA
movici_simulation_core-2.10.6.dist-info/WHEEL
movici_simulation_core-2.10.6.dist-info/entry_points.txt
movici_simulation_core-2.10.6.dist-info/top_level.txt
movici_simulation_core-2.10.6.dist-info/RECORD
