Metadata-Version: 2.1
Name: movici-simulation-core
Version: 2.10.6
Summary: Core package for running Movici geospatial temporal simulations
Home-page: http://www.movici.nl
Author: NGinfra Movici
Author-email: movici@nginfra.nl
License: Movici Public License
Project-URL: Homepage, https://www.movici.nl/
Project-URL: Documentation, https://docs.movici.nl/
Project-URL: Source, https://github.com/nginfra/movici-simulation-core/
Platform: UNKNOWN
Classifier: Development Status :: 4 - Beta
Classifier: Intended Audience :: Science/Research
Classifier: Intended Audience :: Developers
Classifier: License :: Free for non-commercial use
Classifier: License :: Other/Proprietary License
Classifier: Operating System :: Microsoft :: Windows
Classifier: Operating System :: POSIX :: Linux
Classifier: Programming Language :: Python
Classifier: Programming Language :: Python :: 3.8
Classifier: Programming Language :: Python :: 3.9
Classifier: Programming Language :: Python :: 3.10
Classifier: Programming Language :: Python :: 3 :: Only
Classifier: Topic :: Software Development :: Libraries
Classifier: Topic :: Scientific/Engineering :: GIS
License-File: LICENSE
Requires-Dist: click
Requires-Dist: geopandas
Requires-Dist: jsonschema
Requires-Dist: msgpack
Requires-Dist: netCDF4
Requires-Dist: numba (>=0.55)
Requires-Dist: numpy (<1.25,>=1.19.1)
Requires-Dist: orjson (>=3)
Requires-Dist: pandas (>=1.2.0)
Requires-Dist: pydantic (<=2.0.2,>=1.8.2)
Requires-Dist: pydantic-settings
Requires-Dist: pyproj
Requires-Dist: python-dateutil (>=2.8.0)
Requires-Dist: pyzmq
Requires-Dist: Fiona (<1.9.5,>=1.8) ; sys_platform != "win32"
Requires-Dist: Fiona (<1.9.5,>=1.9) ; sys_platform == "win32"
Provides-Extra: all
Requires-Dist: aequilibrae (<=0.9.2,>0.7.4) ; extra == 'all'
Requires-Dist: bandit ; extra == 'all'
Requires-Dist: black ; extra == 'all'
Requires-Dist: bump2version ; extra == 'all'
Requires-Dist: flake8 ; extra == 'all'
Requires-Dist: furo ; extra == 'all'
Requires-Dist: isort ; extra == 'all'
Requires-Dist: movici-geo-query (>=1.1.1) ; extra == 'all'
Requires-Dist: mypy ; extra == 'all'
Requires-Dist: pylint ; extra == 'all'
Requires-Dist: pyproj (>=3.0.1) ; extra == 'all'
Requires-Dist: pytest ; extra == 'all'
Requires-Dist: pytest-cov ; extra == 'all'
Requires-Dist: safety ; extra == 'all'
Requires-Dist: shapely (>=1.7.1) ; extra == 'all'
Requires-Dist: sphinx ; extra == 'all'
Requires-Dist: sphinxcontrib-mermaid ; extra == 'all'
Requires-Dist: sphinxcontrib-plantuml ; extra == 'all'
Provides-Extra: dev
Requires-Dist: bandit ; extra == 'dev'
Requires-Dist: black ; extra == 'dev'
Requires-Dist: bump2version ; extra == 'dev'
Requires-Dist: flake8 ; extra == 'dev'
Requires-Dist: isort ; extra == 'dev'
Requires-Dist: mypy ; extra == 'dev'
Requires-Dist: pylint ; extra == 'dev'
Requires-Dist: pytest ; extra == 'dev'
Requires-Dist: pytest-cov ; extra == 'dev'
Requires-Dist: safety ; extra == 'dev'
Provides-Extra: docs
Requires-Dist: furo ; extra == 'docs'
Requires-Dist: sphinx ; extra == 'docs'
Requires-Dist: sphinxcontrib-mermaid ; extra == 'docs'
Requires-Dist: sphinxcontrib-plantuml ; extra == 'docs'
Provides-Extra: models
Requires-Dist: aequilibrae (<=0.9.2,>0.7.4) ; extra == 'models'
Requires-Dist: movici-geo-query (>=1.1.1) ; extra == 'models'
Requires-Dist: pyproj (>=3.0.1) ; extra == 'models'
Requires-Dist: shapely (>=1.7.1) ; extra == 'models'
